CHANGES.rst
MANIFEST.in
README.rst
setup.py
envoy_webhook_auth_decorator/__init__.py
envoy_webhook_auth_decorator/envoy_webhook_auth_decorator.py
envoy_webhook_auth_decorator/hmac_signature.py
envoy_webhook_auth_decorator.egg-info/PKG-INFO
envoy_webhook_auth_decorator.egg-info/SOURCES.txt
envoy_webhook_auth_decorator.egg-info/dependency_links.txt
envoy_webhook_auth_decorator.egg-info/top_level.txt