Metadata-Version: 1.1
Name: envoy-webhook-auth-decorator
Version: 0.0.3
Summary: Envoy webhook authentication decorator
Home-page: https://github.com/sunwei/envoy-webhook-auth-decorator
Author: Wayde Sun
Author-email: wayde.sun@gmail.com
License: UNKNOWN
Platform: UNKNOWN
Classifier: Development Status :: 4 - Beta
Classifier: Intended Audience :: Developers
Classifier: License :: OSI Approved :: MIT License
Classifier: Natural Language :: English
Classifier: Operating System :: OS Independent
Classifier: Programming Language :: Python
Classifier: Topic :: Software Development :: Libraries :: Python Modules
